{"inkVersion":19,"root":[[{"->":"start"},["done",{"#f":5,"#n":"g-0"}],null],"done",{"start":[["ev",{"VAR?":"murderWeapon"},"str","^scissors","/str","==","/ev",{"->":".^.b","c":true},{"b":["\n","ev",1,"/ev",{"VAR=":"playerFoundWeapon","re":true},"^As you pick up the tool, all the hairs on your arms stand up. You've been trained in observation and analysis, but there's no protocol from headquarters for the prickling feeling you have.","\n","^On their own, scissors aren't an unusual item to see. Any household would have a pair for common tasks, and in this mansion, these might be used specifically for cutting film. But these scissors have blood coating the blades.","\n",{"->":"success"},{"->":"start.2"},null]}],[{"->":".^.b"},{"b":["\n","^On their own, scissors aren't an unusual item to see. Any household would have a pair for common tasks, and in this mansion, these might be used specifically for cutting film. You've seen plenty cases where the criminal turned to the common blades in a fit of passion. But these don't appear to have been touched.","\n","ev","str","^Continue searching","/str","/ev",{"*":".^.c-0","flg":20},{"->":"start.2"},{"c-0":["\n","ev",1,"/ev",{"VAR=":"storyEnd","re":true},"end",{"#f":5}]}]}],"nop","\n",{"#f":1}],"success":[[["ev",{"VAR?":"playerFoundBody"},1,"==","/ev",{"->":".^.b","c":true},{"b":["\n","^That's two pieces of evidence now that have made your hair stand on end. ","ev",{"VAR?":"playerDangerStage"},"str","^high","/str","==",{"VAR?":"playerDangerStage"},"str","^critical","/str","==","||","/ev",[{"->":".^.b","c":true},{"b":["^The sudden death, the bizarre house? There's no denying it: this is unlike any other case you've solved before. Whatever happened in this mansion wasn't just sinister. It was surreal. Maybe even supernatural.",{"->":".^.^.^.17"},null]}],[{"->":".^.b"},{"b":["^You've seen ugly murder cases before, but they didn't turn your stomach like this. Something else is going on, even if you don't understand what.",{"->":".^.^.^.17"},null]}],"nop","^ The only question left, the last fact you can arm yourself with, is determining who perpetrated this act. You'd better hurry and make your accusation.","\n",{"->":".^.^.^.2"},null]}],[{"->":".^.b"},{"b":["\n","ev",{"VAR?":"playerDangerStage"},"str","^high","/str","==",{"VAR?":"playerDangerStage"},"str","^critical","/str","==","||","/ev",[{"->":".^.b","c":true},{"b":["^You have a bad feeling about this case. There's definitely something strange at play, something bad in the air. You don't have a clue yet what it is,",{"->":".^.^.^.16"},null]}],[{"->":".^.b"},{"b":["^You can't put your finger on it, but there's something odd about this case. Something strange in the air. You want to dismiss the idea out of hand,",{"->":".^.^.^.16"},null]}],"nop","^ but you've learned to trust your gut. And your gut is saying to stay sharp and watch your back. Maybe if you have another concrete fact, like the dead body, you'll better understand the truth.","\n",{"->":".^.^.^.2"},null]}],"nop","\n","ev","str","^Continue searching","/str","/ev",{"*":".^.c-0","flg":20},{"c-0":["\n","ev",1,"/ev",{"VAR=":"storyEnd","re":true},"end",{"#f":5}]}],{"#f":1}],"global decl":["ev","str","^","/str",{"VAR=":"playerDangerStage"},"str","^","/str",{"VAR=":"murderer"},0,{"VAR=":"murdererGender"},"str","^","/str",{"VAR=":"victim"},0,{"VAR=":"victimGender"},"str","^","/str",{"VAR=":"hidingSpot"},"str","^","/str",{"VAR=":"murderWeapon"},0,{"VAR=":"weaponType"},"str","^","/str",{"VAR=":"directorAlibi"},"str","^","/str",{"VAR=":"editorAlibi"},"str","^","/str",{"VAR=":"processorAlibi"},"str","^","/str",{"VAR=":"housekeeperAlibi"},"str","^","/str",{"VAR=":"cookAlibi"},"str","^","/str",{"VAR=":"screenwriterAlibi"},"str","^","/str",{"VAR=":"actressAlibi"},"str","^","/str",{"VAR=":"actorAlibi"},0,{"VAR=":"playerFoundKey"},0,{"VAR=":"playerFoundWeapon"},0,{"VAR=":"playerFoundBody"},0,{"VAR=":"playerVisitedDistillery"},0,{"VAR=":"playerKnowsName"},0,{"VAR=":"accuseMurdererSuccess"},0,{"VAR=":"storyEnd"},0,{"VAR=":"gameEnd"},"/ev","end",null],"#f":1}],"listDefs":{}}